fatiguepy/Dirlik.py
fatiguepy/Narrow_Band.py
fatiguepy/Rainflow.py
fatiguepy/Rice.py
fatiguepy/Tovo_Benasciutti.py
fatiguepy/Tovo_Bennasciutti.py
fatiguepy/Wirsching_Light.py
fatiguepy/Zhao_Baker.py
fatiguepy/__init__.py
fatiguepy/alpha075.py
fatiguepy/alpha0dot75.py
fatiguepy/prob_dist_peaks.py
fatiguepy/prob_moment.py
fatiguepy-2.3.2.dist-info/LICENSE
fatiguepy-2.3.2.dist-info/METADATA
fatiguepy-2.3.2.dist-info/WHEEL
fatiguepy-2.3.2.dist-info/top_level.txt
fatiguepy-2.3.2.dist-info/RECORD
