Metadata-Version: 2.1
Name: fatiguepy
Version: 2.3.2
Summary: Package to estimate life of random fatigue history with frequency domain methods
Home-page: https://github.com/thiagonds65/fatiguepy
Author: Thiago Santos
Author-email: thiagonds@id.uff.br
License: MIT
Platform: UNKNOWN
